sage/__init__.py
sage/cli/__init__.py
sage/cli/create.py
sage/cli/delete.py
sage/cli/list.py
sage/cli/main.py
sage/cli/rename.py
sage/cli/stopwatch.py
sage/cli/timer.py
sage/cli/update.py
sage/clocks/__init__.py
sage/clocks/clock.py
sage/clocks/constants.py
sage/clocks/renderer.py
sage/clocks/resize.py
sage/clocks/stopwatch.py
sage/clocks/timer.py
sage/common/__init__.py
sage/common/conversions.py
sage/common/formatting.py
sage/config/__init__.py
sage/config/presets.py
sage/config/sounds.py
sounds/timesup.mp3
sage_timer-0.1.2.dist-info/METADATA
sage_timer-0.1.2.dist-info/WHEEL
sage_timer-0.1.2.dist-info/entry_points.txt
sage_timer-0.1.2.dist-info/licenses/LICENSE
sage_timer-0.1.2.dist-info/RECORD
