Metadata-Version: 2.4
Name: sage-timer
Version: 0.1.2
Summary: Sage is an easy-to-use command line timer that looks good and accepts natural language time formats.
Project-URL: Repository, https://github.com/nmsalvatore/sage
Project-URL: Issues, https://github.com/nmsalvatore/sage/issues
Author-email: Nicholas Salvatore <nmsalvatore@protonmail.com>
License-Expression: MIT
License-File: LICENSE
Keywords: cli,curses,pomodoro,productivity,stopwatch,terminal,timer
Classifier: Development Status :: 4 - Beta
Classifier: Environment :: Console
Classifier: Environment :: Console :: Curses
Classifier: Intended Audience :: Developers
Classifier: Intended Audience :: End Users/Desktop
Classifier: License :: OSI Approved :: MIT License
Classifier: Operating System :: OS Independent
Classifier: Programming Language :: Python :: 3
Classifier: Programming Language :: Python :: 3.10
Classifier: Programming Language :: Python :: 3.11
Classifier: Programming Language :: Python :: 3.12
Classifier: Programming Language :: Python :: 3.13
Classifier: Topic :: Office/Business :: Scheduling
Classifier: Topic :: System :: Shells
Classifier: Topic :: Terminals
Classifier: Topic :: Utilities
Requires-Python: >=3.10
Requires-Dist: click>=8.2.1
Requires-Dist: nava>=0.7
Requires-Dist: platformdirs>=4.3.8
